junk-email-collector/__init__.py
junk-email-collector/junk_email_collector.py
junk_email_collector/__init__.py
junk_email_collector/junk_email_collector.py
junk_email_collector-1.0.0.dist-info/METADATA
junk_email_collector-1.0.0.dist-info/WHEEL
junk_email_collector-1.0.0.dist-info/top_level.txt
junk_email_collector-1.0.0.dist-info/zip-safe
junk_email_collector-1.0.0.dist-info/RECORD
