Metadata-Version: 2.1
Name: junk-email-collector
Version: 1.0.0
Summary: Download raw Junk/Spam emails using IMAP.
Home-page: https://github.com/wesinator/junk-email-collector
Author: wesinator
License: UNKNOWN
Keywords: spam
Platform: UNKNOWN
Classifier: Development Status :: 4 - Beta
Classifier: Intended Audience :: Developers
Classifier: License :: OSI Approved :: GNU General Public License v3 or later (GPLv3+)
Classifier: Natural Language :: English
Classifier: Programming Language :: Python :: 3
Classifier: Programming Language :: Python :: 3.5
Classifier: Programming Language :: Python :: 3.6
Classifier: Programming Language :: Python :: 3.7
Requires-Dist: imbox
